fastapiccache/__init__.py
fastapiccache/cache.py
fastapiccache-0.1.1.dist-info/METADATA
fastapiccache-0.1.1.dist-info/WHEEL
fastapiccache-0.1.1.dist-info/RECORD
