Metadata-Version: 2.1
Name: fastapiccache
Version: 0.1.1
Summary: 
Home-page: https://github.com/dsal3389/fastapicache
License: MIT
Author: Daniel Sonbolian
Author-email: dsal3389@gmail.com
Requires-Python: >=3.10,<4.0
Classifier: License :: OSI Approved :: MIT License
Classifier: Programming Language :: Python :: 3
Classifier: Programming Language :: Python :: 3.10
Classifier: Programming Language :: Python :: 3.11
Project-URL: Repository, https://github.com/dsal3389/fastapicache
